aftercovid/__init__.py
aftercovid/__main__.py
aftercovid/data/__init__.py
aftercovid/data/data_hopkins.py
aftercovid/data/france_bin.bmp
aftercovid/data/image_grid.py
aftercovid/data/image_helper.py
aftercovid/grid/__init__.py
aftercovid/grid/grid_map_sir.py
aftercovid/models/__init__.py
aftercovid/models/_base_sir.py
aftercovid/models/_base_sir_estimation.py
aftercovid/models/_base_sir_sim.py
aftercovid/models/_sympy_helper.py
aftercovid/models/covid_sird.py
aftercovid/models/covid_sird_cst.py
aftercovid/models/epidemic_regressor.py
aftercovid/models/model_estimation.py
aftercovid/optim/__init__.py
aftercovid/optim/sgd.py
aftercovid/preprocess/__init__.py
aftercovid/preprocess/ts.py
aftercovid-0.1.2.dist-info/LICENSE.txt
aftercovid-0.1.2.dist-info/METADATA
aftercovid-0.1.2.dist-info/WHEEL
aftercovid-0.1.2.dist-info/top_level.txt
aftercovid-0.1.2.dist-info/RECORD
