Metadata-Version: 2.1
Name: aftercovid
Version: 0.1.2
Summary: Code, ideas about COVID epidemics
Home-page: https://github.com/sdpython/aftercovid
Author: Xavier Dupré, ...
Author-email: xavier.dupre@gmail.com
License: UNKNOWN
Platform: UNKNOWN
Requires-Dist: cython
Requires-Dist: fire
Requires-Dist: numpy
Requires-Dist: pandas
Requires-Dist: scikit-image
Requires-Dist: scikit-learn
Requires-Dist: scipy
Requires-Dist: sympy
